SIK/__init__.py
SIK/sica.py
SIK/ssica.py
SIK-2.1.6.dist-info/LICENSE
SIK-2.1.6.dist-info/METADATA
SIK-2.1.6.dist-info/WHEEL
SIK-2.1.6.dist-info/top_level.txt
SIK-2.1.6.dist-info/RECORD
